LICENSE
dunebuggy/__init__.py
dunebuggy/core/__init__.py
dunebuggy/core/dune.py
dunebuggy/core/dunequery.py
dunebuggy/core/exceptions.py
dunebuggy/core/gqlquerier.py
dunebuggy/models/__init__.py
dunebuggy/models/constants.py
dunebuggy/models/gqlqueries.py
dunebuggy/models/query.py
dunebuggy-1.0.8.dist-info/LICENSE
dunebuggy-1.0.8.dist-info/WHEEL
dunebuggy-1.0.8.dist-info/METADATA
dunebuggy-1.0.8.dist-info/RECORD
