Metadata-Version: 2.1
Name: dunebuggy
Version: 1.0.8
Summary: A lightweight (unofficial) Python SDK for Dune.com
Home-page: https://github.com/rysuds/dunebuggy
License: MIT
Author: rysuds
Author-email: ryan.sudhakaran@gmail.com
Requires-Python: >=3.9
Classifier: License :: OSI Approved :: MIT License
Classifier: Programming Language :: Python :: 3
Classifier: Programming Language :: Python :: 3.10
Classifier: Programming Language :: Python :: 3.9
Requires-Dist: httpx (>=0.18.2)
Requires-Dist: numpy (>=1.21,<1.23)
Requires-Dist: pandas (>=1.2.4)
Requires-Dist: pydantic (>=1.8.2)
Requires-Dist: sqlparse (>=0.4.2)
Project-URL: Repository, https://github.com/rysuds/dunebuggy
